pygios
pygios/__init__
