Metadata-Version: 1.0
Name: pygios
Version: 0.0.3
Summary: Python based Nagios plugs made simple
Home-page: UNKNOWN
Author: Adam DePrince
Author-email: deprince@googlealumni.com
License: UNKNOWN
Platform: UNKNOWN
